examples/__init__.py
examples/auth/__init__.py
examples/auth/app.py
examples/auth/config.py
examples/auth-flask-login/__init__.py
examples/auth-flask-login/app.py
examples/forms/__init__.py
examples/forms/app.py
examples/geo_alchemy/__init__.py
examples/geo_alchemy/app.py
examples/geo_alchemy/config.py
examples/layout/__init__.py
examples/layout/app.py
examples/layout_bootstrap3/__init__.py
examples/layout_bootstrap3/app.py
examples/quickstart/__init__.py
examples/quickstart/app.py
examples/quickstart/app2.py
examples/quickstart/app3.py
examples/simple/__init__.py
examples/simple/app.py
examples/sqla/__init__.py
examples/sqla/app.py
examples/sqla/app2.py
examples/sqla-custom-filter/__init__.py
examples/sqla-custom-filter/app.py
examples/sqla-filter-selectable/__init__.py
examples/sqla-filter-selectable/app.py
examples/sqla-hybrid_property/__init__.py
examples/sqla-hybrid_property/app.py
flask_admin/__init__.py
flask_admin/_backwards.py
flask_admin/_compat.py
flask_admin/actions.py
flask_admin/babel.py
flask_admin/base.py
flask_admin/consts.py
flask_admin/helpers.py
flask_admin/menu.py
flask_admin/tools.py
flask_admin/contrib/__init__.py
flask_admin/contrib/rediscli.py
flask_admin/contrib/appengine/__init__.py
flask_admin/contrib/appengine/view.py
flask_admin/contrib/fileadmin/__init__.py
flask_admin/contrib/fileadmin/s3.py
flask_admin/contrib/geoa/__init__.py
flask_admin/contrib/geoa/fields.py
flask_admin/contrib/geoa/form.py
flask_admin/contrib/geoa/typefmt.py
flask_admin/contrib/geoa/view.py
flask_admin/contrib/geoa/widgets.py
flask_admin/contrib/mongoengine/__init__.py
flask_admin/contrib/mongoengine/ajax.py
flask_admin/contrib/mongoengine/fields.py
flask_admin/contrib/mongoengine/filters.py
flask_admin/contrib/mongoengine/form.py
flask_admin/contrib/mongoengine/helpers.py
flask_admin/contrib/mongoengine/subdoc.py
flask_admin/contrib/mongoengine/tools.py
flask_admin/contrib/mongoengine/typefmt.py
flaskpress_flask_admin-1.4.2.2.dist-info/DESCRIPTION.rst
flaskpress_flask_admin-1.4.2.2.dist-info/METADATA
flaskpress_flask_admin-1.4.2.2.dist-info/RECORD
flaskpress_flask_admin-1.4.2.2.dist-info/WHEEL
flaskpress_flask_admin-1.4.2.2.dist-info/metadata.json
flaskpress_flask_admin-1.4.2.2.dist-info/top_level.txt
