Metadata-Version: 2.0
Name: flaskpress-flask-admin
Version: 1.4.2.2
Summary: Fork of Flask-Admin for flaskpress
Home-page: https://github.com/infrascloudy/flaskpress-flask-admin
Author: InfrasCloudy, @allanice001
Author-email: support@linaccess.za.net
License: BSD
Platform: any
Classifier: Development Status :: 4 - Beta
Classifier: Environment :: Web Environment
Classifier: Intended Audience :: Developers
Classifier: License :: OSI Approved :: BSD License
Classifier: Operating System :: OS Independent
Classifier: Programming Language :: Python
Classifier: Topic :: Software Development :: Libraries :: Python Modules
Classifier: Programming Language :: Python :: 2.7
Classifier: Programming Language :: Python :: 2.6
Classifier: Programming Language :: Python :: 3.3
Classifier: Programming Language :: Python :: 3.4
Classifier: Programming Language :: Python :: 3.5
Requires-Dist: Flask (>=0.7)
Requires-Dist: wtforms
